pakegeName/__init__.py
pakegeName/test.py
pakegeName-0.0.2.dist-info/LICENSE
pakegeName-0.0.2.dist-info/METADATA
pakegeName-0.0.2.dist-info/WHEEL
pakegeName-0.0.2.dist-info/top_level.txt
pakegeName-0.0.2.dist-info/RECORD
